gammagang.py
gammagang-2.0.0.dist-info/LICENSE
gammagang-2.0.0.dist-info/METADATA
gammagang-2.0.0.dist-info/WHEEL
gammagang-2.0.0.dist-info/top_level.txt
gammagang-2.0.0.dist-info/RECORD
