Metadata-Version: 2.1
Name: gammagang
Version: 2.0.0
Summary: GammaGang Package for distribution
Home-page: UNKNOWN
Author: Ryan Watts
License: UNKNOWN
Platform: UNKNOWN
Classifier: Programming Language :: Python :: 3
Classifier: License :: OSI Approved :: MIT License
Classifier: Operating System :: OS Independent
Requires-Python: >=3
Requires-Dist: pandas (==1.1.3)
Requires-Dist: boto3
